codeflow_solver/__init__.py
codeflow_solver/py.typed
codeflow_solver/cli/__init__.py
codeflow_solver/cli/main.py
codeflow_solver/docs/MATHEMATICAL_DETAILS.md
codeflow_solver/set_cover/__init__.py
codeflow_solver/set_cover/initializer.py
codeflow_solver/solver/__init__.py
codeflow_solver/solver/optimizer.py
codeflow_solver/solver/set_cover_solver.py
codeflow_solver/utils/__init__.py
codeflow_solver/utils/data_structures.py
codeflow_solver/utils/sarif_parser.py
codeflow_solver/utils/severity_mapper.py
codeflow_solver-1.0.0.dist-info/METADATA
codeflow_solver-1.0.0.dist-info/WHEEL
codeflow_solver-1.0.0.dist-info/entry_points.txt
codeflow_solver-1.0.0.dist-info/RECORD
