Metadata-Version: 2.4
Name: codeflow-solver
Version: 1.0.0
Summary: A tool that finds the minimum number of code fixes needed to eliminate vulnerabilities from SARIF output
Author: Amine Boudraa, Gianfranco Romani, Yassine Ilmi
Requires-Python: >=3.9
Requires-Dist: ortools>=9.0.0
